<?xml version='1.0' encoding='UTF-8'?>
<config-element id="3f10571d-1b0c-41d0-909c-4ecc8bccc428" version="0.0.0">
  <display-name><![CDATA[network]]></display-name>
  <atts>
    <att name="smtp" type="string" read-only="false">
      <value encoded="n"><![CDATA[ 192.168.1.10]]></value>
    </att>
    <att name="dns" type="string" read-only="false">
      <value encoded="n"><![CDATA[192.168.1.13]]></value>
    </att>
    <att name="user" type="string" read-only="false">
      <value encoded="n"><![CDATA[administrator@avengers.com]]></value>
    </att>
    <att name="ad" type="string" read-only="false">
      <value encoded="n"><![CDATA[ad.avengers.com]]></value>
    </att>
  </atts>
</config-element>